monarch_cli/__init__.py
monarch_cli/commands/__init__.py
monarch_cli/commands/accounts.py
monarch_cli/commands/auth.py
monarch_cli/commands/budgets.py
monarch_cli/commands/cashflow.py
monarch_cli/commands/categories.py
monarch_cli/commands/transactions.py
monarch_cli/core/__init__.py
monarch_cli/core/adapter.py
monarch_cli/core/async_utils.py
monarch_cli/core/config.py
monarch_cli/core/dates.py
monarch_cli/core/error_handler.py
monarch_cli/core/exceptions.py
monarch_cli/core/retry.py
monarch_cli/core/session.py
monarch_cli/main.py
monarch_cli/output/__init__.py
monarch_cli/output/plain.py
monarch_cli/output/progress.py
monarch_cli/py.typed
monarch_cli/services/__init__.py
monarch_cli/services/accounts.py
monarch_cli/transformers/__init__.py
monarch_cli/transformers/accounts.py
monarch_cli/transformers/cashflow.py
monarch_cli/transformers/transactions.py
monarch_cli-0.1.0.dist-info/WHEEL
monarch_cli-0.1.0.dist-info/entry_points.txt
monarch_cli-0.1.0.dist-info/METADATA
monarch_cli-0.1.0.dist-info/RECORD
