Metadata-Version: 2.3
Name: monarch-cli
Version: 0.1.0
Summary: CLI wrapper around monarchmoneycommunity for AI agent integration with Monarch Money
Keywords: monarch,money,finance,cli,personal-finance,budgeting
Author: Christian Catalan
Author-email: Christian Catalan <crcatala@gmail.com>
License: MIT
Classifier: Development Status :: 4 - Beta
Classifier: Environment :: Console
Classifier: Intended Audience :: Developers
Classifier: Intended Audience :: End Users/Desktop
Classifier: License :: OSI Approved :: MIT License
Classifier: Operating System :: OS Independent
Classifier: Programming Language :: Python :: 3
Classifier: Programming Language :: Python :: 3.12
Classifier: Programming Language :: Python :: 3.13
Classifier: Topic :: Office/Business :: Financial
Classifier: Topic :: Utilities
Classifier: Typing :: Typed
Requires-Dist: typer[all]>=0.9.0
Requires-Dist: monarchmoneycommunity>=1.0.0
Requires-Dist: keyring>=24.0.0
Requires-Dist: rich>=13.0.0
Requires-Dist: platformdirs>=4.0.0
Requires-Dist: pytest>=8.0.0 ; extra == 'dev'
Requires-Dist: pytest-asyncio>=0.23.0 ; extra == 'dev'
Requires-Dist: pytest-cov>=4.0.0 ; extra == 'dev'
Requires-Dist: ruff>=0.4.0 ; extra == 'dev'
Requires-Dist: mypy>=1.10.0 ; extra == 'dev'
Requires-Dist: prek>=0.2.30 ; extra == 'dev'
Requires-Dist: readme-renderer[md]>=44.0 ; extra == 'dev'
Requires-Dist: twine>=5.0.0 ; extra == 'dev'
Requires-Python: >=3.12
Project-URL: Changelog, https://github.com/crcatala/monarch-cli/blob/main/CHANGELOG.md
Project-URL: Documentation, https://github.com/crcatala/monarch-cli#readme
Project-URL: Homepage, https://github.com/crcatala/monarch-cli
Project-URL: Issues, https://github.com/crcatala/monarch-cli/issues
Project-URL: Repository, https://github.com/crcatala/monarch-cli
Provides-Extra: dev
